{
  "parent": "minecraft:recipes/root",
  "criteria": {
    "has_TagKey[minecraft:item / c:nuggets/aluminum]_nugget": {
      "conditions": {
        "items": [
          {
            "items": "#c:nuggets/aluminum"
          }
        ]
      },
      "trigger": "minecraft:inventory_changed"
    },
    "has_the_recipe": {
      "conditions": {
        "recipe": "alltheores:aluminum_ingot"
      },
      "trigger": "minecraft:recipe_unlocked"
    }
  },
  "requirements": [
    [
      "has_the_recipe",
      "has_TagKey[minecraft:item / c:nuggets/aluminum]_nugget"
    ]
  ],
  "rewards": {
    "recipes": [
      "alltheores:aluminum_ingot"
    ]
  }
}